LICENSE
MANIFEST.in
README.md
setup.py
bin/harvest
harvest/__init__.py
harvest/config.py
harvest/decorators.py
harvest/utils.py
harvest.egg-info/PKG-INFO
harvest.egg-info/SOURCES.txt
harvest.egg-info/dependency_links.txt
harvest.egg-info/requires.txt
harvest.egg-info/top_level.txt
harvest/commands/__init__.py
harvest/commands/init.py
harvest/commands/init_demo.py
harvest/commands/update.py