Metadata-Version: 1.1
Name: harvest
Version: 2.2.0
Summary: Harvest Command Line Tool
Home-page: https://github.com/cbmi/harvest/
Author: The Children's Hospital of Philadelphia
Author-email: cbmisupport@email.chop.edu
License: BSD
Keywords: harvest metadata avocado serrano cilantro django
Platform: UNKNOWN
Classifier: Development Status :: 4 - Beta
Classifier: License :: OSI Approved :: BSD License
Classifier: Programming Language :: Python :: 2.6
Classifier: Programming Language :: Python :: 2.7
Classifier: Framework :: Django
Classifier: Topic :: Internet :: WWW/HTTP
Classifier: Intended Audience :: Developers
Classifier: Intended Audience :: Science/Research
Classifier: Intended Audience :: Healthcare Industry
Classifier: Intended Audience :: Information Technology
